LICENSE
README.md
fmi_ai_judge/__init__.py
fmi_ai_judge/cli.py
fmi_ai_judge/problems.yaml
fmi_ai_judge/tests/frog-leap/check.py
fmi_ai_judge/tests/frog-leap/t01.in
fmi_ai_judge/tests/frog-leap/t02.in
fmi_ai_judge/tests/frog-leap/t03.in
fmi_ai_judge/tests/frog-leap/t04.in
fmi_ai_judge/tests/frog-leap/t05.in
fmi_ai_judge/tests/frog-leap/t06.in
fmi_ai_judge/tests/frog-leap/tests.yaml
fmi_ai_judge/tests/knapsack/check.py
fmi_ai_judge/tests/knapsack/t01.in
fmi_ai_judge/tests/knapsack/t01.out
fmi_ai_judge/tests/knapsack/t02.in
fmi_ai_judge/tests/knapsack/t02.out
fmi_ai_judge/tests/knapsack/tests.yaml
fmi_ai_judge/tests/n-puzzle/check.py
fmi_ai_judge/tests/n-puzzle/t01.in
fmi_ai_judge/tests/n-puzzle/t01.out
fmi_ai_judge/tests/n-puzzle/t02.in
fmi_ai_judge/tests/n-puzzle/t02.out
fmi_ai_judge/tests/n-puzzle/t03.in
fmi_ai_judge/tests/n-puzzle/t03.out
fmi_ai_judge/tests/n-puzzle/t04.in
fmi_ai_judge/tests/n-puzzle/t04.out
fmi_ai_judge/tests/n-puzzle/t05.in
fmi_ai_judge/tests/n-puzzle/t05.out
fmi_ai_judge/tests/n-puzzle/t06.in
fmi_ai_judge/tests/n-puzzle/t06.out
fmi_ai_judge/tests/n-puzzle/t07.in
fmi_ai_judge/tests/n-puzzle/t07.out
fmi_ai_judge/tests/n-puzzle/t08.in
fmi_ai_judge/tests/n-puzzle/t08.out
fmi_ai_judge/tests/n-puzzle/t09.in
fmi_ai_judge/tests/n-puzzle/t09.out
fmi_ai_judge/tests/n-puzzle/t10.in
fmi_ai_judge/tests/n-puzzle/t10.out
fmi_ai_judge/tests/n-puzzle/t11.in
fmi_ai_judge/tests/n-puzzle/t11.out
fmi_ai_judge/tests/n-puzzle/tests.yaml
fmi_ai_judge/tests/n-queens/check.py
fmi_ai_judge/tests/n-queens/t01.in
fmi_ai_judge/tests/n-queens/t01.out
fmi_ai_judge/tests/n-queens/t02.in
fmi_ai_judge/tests/n-queens/t02.out
fmi_ai_judge/tests/n-queens/t03.in
fmi_ai_judge/tests/n-queens/t03.out
fmi_ai_judge/tests/n-queens/t04.in
fmi_ai_judge/tests/n-queens/t05.in
fmi_ai_judge/tests/n-queens/t06.in
fmi_ai_judge/tests/n-queens/t07.in
fmi_ai_judge/tests/n-queens/t08.in
fmi_ai_judge/tests/n-queens/t09.in
fmi_ai_judge/tests/n-queens/t10.in
fmi_ai_judge/tests/n-queens/t11.in
fmi_ai_judge-0.2.5.dist-info/METADATA
fmi_ai_judge-0.2.5.dist-info/WHEEL
fmi_ai_judge-0.2.5.dist-info/entry_points.txt
fmi_ai_judge-0.2.5.dist-info/licenses/LICENSE
fmi_ai_judge-0.2.5.dist-info/RECORD
