Metadata-Version: 2.4
Name: fmi-ai-judge
Version: 0.2.5
Summary: Student-first CLI to run AI homework solutions against official tests.
Project-URL: Homepage, https://github.com/BorisVelichkov/fmi-ai-judge
Project-URL: Issues, https://github.com/BorisVelichkov/fmi-ai-judge/issues
Author-email: Boris Velichkov <boris.velichkov@fmi.uni-sofia.bg>
License: BSD 3-Clause License
License-File: LICENSE
Classifier: Environment :: Console
Classifier: License :: OSI Approved :: BSD License
Classifier: Operating System :: OS Independent
Classifier: Programming Language :: Python :: 3 :: Only
Classifier: Programming Language :: Python :: 3.8
Classifier: Programming Language :: Python :: 3.9
Classifier: Programming Language :: Python :: 3.10
Classifier: Programming Language :: Python :: 3.11
Classifier: Programming Language :: Python :: 3.12
Requires-Python: >=3.8
Requires-Dist: importlib-resources>=6.4; python_version < '3.9'
Requires-Dist: pyyaml>=6.0
